koppeltaal/__init__.py
koppeltaal/codes.py
koppeltaal/compat.py
koppeltaal/connector.py
koppeltaal/console.py
koppeltaal/definitions.py
koppeltaal/interfaces.py
koppeltaal/logger.py
koppeltaal/models.py
koppeltaal/testing.py
koppeltaal/transport.py
koppeltaal/utils.py
koppeltaal/fhir/__init__.py
koppeltaal/fhir/bundle.py
koppeltaal/fhir/packer.py
koppeltaal/fhir/registry.py
koppeltaal/fhir/resource.py
koppeltaal/fhir/xml.py
koppeltaal/tests/__init__.py
koppeltaal/tests/test_activitydefinition.py
koppeltaal/tests/test_careteam.py
koppeltaal/tests/test_connector.py
koppeltaal/tests/test_definitions.py
koppeltaal/tests/test_integration.py
koppeltaal/tests/fixtures/activities_game.json
koppeltaal/tests/fixtures/bundle_one_error.json
koppeltaal/tests/fixtures/bundle_one_message.json
koppeltaal/tests/fixtures/bundle_one_message_same_source.json
koppeltaal/tests/fixtures/bundle_post_activitydefinition_failed.json
koppeltaal/tests/fixtures/bundle_post_activitydefinition_ok.json
koppeltaal/tests/fixtures/bundle_post_careplan_failed.json
koppeltaal/tests/fixtures/bundle_post_careplan_ok.json
koppeltaal/tests/fixtures/bundle_zero_messages.json
koppeltaal/tests/fixtures/operation_outcome.json
koppeltaal/tests/fixtures/resource_put_message.json
koppeltaal-1.3.5.14.dist-info/LICENSE.md
koppeltaal-1.3.5.14.dist-info/METADATA
koppeltaal-1.3.5.14.dist-info/WHEEL
koppeltaal-1.3.5.14.dist-info/entry_points.txt
koppeltaal-1.3.5.14.dist-info/top_level.txt
koppeltaal-1.3.5.14.dist-info/RECORD
