Metadata-Version: 2.1
Name: koppeltaal
Version: 1.3.5.14
Home-page: https://github.com/Koppeltaal/Koppeltaal-Python-Connector
Author: Koppeltaal community
License: AGPL
Classifier: Development Status :: 5 - Production/Stable
Classifier: Environment :: Console
Classifier: Environment :: Web Environment
Classifier: Intended Audience :: Developers
Classifier: License :: OSI Approved :: GNU Affero General Public License v3
Classifier: Natural Language :: Dutch
Classifier: Natural Language :: English
Classifier: Operating System :: OS Independent
Classifier: Programming Language :: Python :: 2.7
Classifier: Programming Language :: Python :: 2
Classifier: Programming Language :: Python :: 3.6
Classifier: Programming Language :: Python :: 3.7
Classifier: Programming Language :: Python :: 3.8
Classifier: Programming Language :: Python :: 3
Classifier: Programming Language :: Python
Classifier: Topic :: Internet :: WWW/HTTP
Classifier: Topic :: Software Development :: Libraries :: Python Modules
License-File: LICENSE.md
Requires-Dist: six
Requires-Dist: lxml
Requires-Dist: python-dateutil
Requires-Dist: requests
Requires-Dist: setuptools
Requires-Dist: zope.interface >=4.4
Provides-Extra: test
Requires-Dist: PyHamcrest >=1.9 ; extra == 'test'
Requires-Dist: selenium >=3.8 ; extra == 'test'
